lexical/__init__.py
lexical/tests/__init__.py
lexical/tests/sql_test.py
lexical-0.0.5.dist-info/DESCRIPTION.rst
lexical-0.0.5.dist-info/METADATA
lexical-0.0.5.dist-info/RECORD
lexical-0.0.5.dist-info/WHEEL
lexical-0.0.5.dist-info/metadata.json
lexical-0.0.5.dist-info/top_level.txt
