Metadata-Version: 2.0
Name: lexical
Version: 0.0.5
Summary: Simple Lexical Analyser
Home-page: UNKNOWN
Author: Guto Maia
Author-email: guto@guto.net
License: UNKNOWN
Keywords: web
Platform: UNKNOWN
Classifier: Programming Language :: Python
